jupyterlab_vpython/__init__.py
jupyterlab_vpython/_version.py
jupyterlab_vpython-3.1.7.data/data/share/jupyter/labextensions/jupyterlab_vpython/build_log.json
jupyterlab_vpython-3.1.7.data/data/share/jupyter/labextensions/jupyterlab_vpython/package.json
jupyterlab_vpython-3.1.7.data/data/share/jupyter/labextensions/jupyterlab_vpython/static/003822ed55ad9191e071.png
jupyterlab_vpython-3.1.7.data/data/share/jupyter/labextensions/jupyterlab_vpython/static/1c502185df5195d2045e.png
jupyterlab_vpython-3.1.7.data/data/share/jupyter/labextensions/jupyterlab_vpython/static/1c88a762a4cafeafb9c5.png
jupyterlab_vpython-3.1.7.data/data/share/jupyter/labextensions/jupyterlab_vpython/static/2889b4f65c97dbec5131.png
jupyterlab_vpython-3.1.7.data/data/share/jupyter/labextensions/jupyterlab_vpython/static/31b69d43ded5ece6deee.png
jupyterlab_vpython-3.1.7.data/data/share/jupyter/labextensions/jupyterlab_vpython/static/3d3e274632c78c97b550.png
jupyterlab_vpython-3.1.7.data/data/share/jupyter/labextensions/jupyterlab_vpython/static/44e1f3a18b99ddc15c8b.jpg
jupyterlab_vpython-3.1.7.data/data/share/jupyter/labextensions/jupyterlab_vpython/static/4d8a40a5c37ea1cb549b.png
jupyterlab_vpython-3.1.7.data/data/share/jupyter/labextensions/jupyterlab_vpython/static/51aaab801da100c14074.png
jupyterlab_vpython-3.1.7.data/data/share/jupyter/labextensions/jupyterlab_vpython/static/5370afb860c636965872.png
jupyterlab_vpython-3.1.7.data/data/share/jupyter/labextensions/jupyterlab_vpython/static/6a35af3ff9d6f57c4323.png
jupyterlab_vpython-3.1.7.data/data/share/jupyter/labextensions/jupyterlab_vpython/static/948350c94c94def167cf.png
jupyterlab_vpython-3.1.7.data/data/share/jupyter/labextensions/jupyterlab_vpython/static/9e867b8f308f2187cf25.png
jupyterlab_vpython-3.1.7.data/data/share/jupyter/labextensions/jupyterlab_vpython/static/b2362b3c381496437c4e.png
jupyterlab_vpython-3.1.7.data/data/share/jupyter/labextensions/jupyterlab_vpython/static/fa3ac7cb805fc218a80c.png
jupyterlab_vpython-3.1.7.dist-info/METADATA
jupyterlab_vpython-3.1.7.dist-info/WHEEL
jupyterlab_vpython-3.1.7.dist-info/licenses/LICENSE
jupyterlab_vpython-3.1.7.dist-info/RECORD
