Metadata-Version: 2.1
Name: jupyterlab_vpython
Version: 3.1.7
Summary: A VPython extension for JupyterLab
Project-URL: Homepage, https://github.com/jcoady/jupyterlab_vpython
Project-URL: Bug Tracker, https://github.com/jcoady/jupyterlab_vpython/issues
Project-URL: Repository, https://github.com/jcoady/jupyterlab_vpython.git
Author-email: John Coady <johncoady@shaw.ca>
License: BSD 3-Clause License
License-File: LICENSE
Classifier: Framework :: Jupyter
Classifier: Framework :: Jupyter :: JupyterLab
Classifier: Framework :: Jupyter :: JupyterLab :: 4
Classifier: Framework :: Jupyter :: JupyterLab :: Extensions
Classifier: Framework :: Jupyter :: JupyterLab :: Extensions :: Prebuilt
Classifier: License :: OSI Approved :: BSD License
Classifier: Programming Language :: Python
Classifier: Programming Language :: Python :: 3
Classifier: Programming Language :: Python :: 3.8
Classifier: Programming Language :: Python :: 3.9
Classifier: Programming Language :: Python :: 3.10
Classifier: Programming Language :: Python :: 3.11
Classifier: Programming Language :: Python :: 3.12
Requires-Python: >=3.8
